gaffe/__init__.py
gaffe/error.py
gaffe/mypy.py
gaffe/py.typed
gaffe/raises.py
gaffe-0.3.0.dist-info/LICENSE
gaffe-0.3.0.dist-info/METADATA
gaffe-0.3.0.dist-info/WHEEL
gaffe-0.3.0.dist-info/RECORD
