Metadata-Version: 2.1
Name: gaffe
Version: 0.3.0
Summary: Simple structured exceptions for python.
Home-page: https://github.com/kodemore/gaffe
License: MIT
Keywords: error,exception,structured,simple,gaffe
Author: Dawid Kraczkowski
Author-email: dawid.kraczkowski@gmail.com
Requires-Python: >=3.8,<4.0
Classifier: License :: OSI Approved :: MIT License
Classifier: Programming Language :: Python :: 3
Classifier: Programming Language :: Python :: 3.8
Classifier: Programming Language :: Python :: 3.9
Classifier: Programming Language :: Python :: 3.10
Classifier: Programming Language :: Python :: 3.11
Classifier: Topic :: Software Development :: Libraries
Classifier: Topic :: Software Development :: Libraries :: Python Modules
Project-URL: Documentation, https://github.com/kodemore/gaffe
Project-URL: Repository, https://github.com/kodemore/gaffe
